talib/abstract.py
talib/common.pxd
talib/_abstract.pxi
talib/_stream.pxi
talib/_ta_lib.pyx
talib/_version.py
talib/deprecated.py
talib/__init__.py
talib/stream.py
talib/_common.pxi
talib/_ta_lib.pxd
talib/_ta_lib.cpython-39-darwin.so
talib/_func.pxi
talib/.dylibs/libta_lib.0.0.0.dylib
TA_lib_zipline-0.4.27.dev0.dist-info/RECORD
TA_lib_zipline-0.4.27.dev0.dist-info/LICENSE
TA_lib_zipline-0.4.27.dev0.dist-info/WHEEL
TA_lib_zipline-0.4.27.dev0.dist-info/top_level.txt
TA_lib_zipline-0.4.27.dev0.dist-info/METADATA
