Metadata-Version: 2.1
Name: TA-lib-zipline
Version: 0.4.27.dev0
Summary: A backtester for trading algorithms
Home-page: http://github.com/mrjbq7/ta-lib
Download-URL: https://github.com/mrjbq7/ta-lib/releases
Author: John Benediktsson
Author-email: mrjbq7@gmail.com
License: BSD
Classifier: Development Status :: 5 - Production/Stable
Classifier: License :: OSI Approved :: BSD License
Classifier: Natural Language :: English
Classifier: Operating System :: Unix
Classifier: Operating System :: POSIX
Classifier: Operating System :: MacOS :: MacOS X
Classifier: Operating System :: Microsoft :: Windows
Classifier: Programming Language :: Python
Classifier: Programming Language :: Python :: 3.7
Classifier: Programming Language :: Python :: 3.8
Classifier: Programming Language :: Python :: 3.9
Classifier: Programming Language :: Python :: 3.10
Classifier: Intended Audience :: Science/Research
Classifier: Intended Audience :: Financial and Insurance Industry
Classifier: Topic :: Office/Business :: Financial :: Investment
Classifier: Topic :: Scientific/Engineering :: Mathematics
Classifier: Topic :: Scientific/Engineering :: Information Analysis
Classifier: Topic :: System :: Distributed Computing
Requires-Python: >=3.7
License-File: LICENSE
Requires-Dist: numpy (<1.23)
Provides-Extra: all
Requires-Dist: flake8 (>=3.9.1) ; extra == 'all'
Requires-Dist: black ; extra == 'all'
Requires-Dist: pre-commit (>=2.12.1) ; extra == 'all'
Requires-Dist: tox ; extra == 'all'
Requires-Dist: pytest (==6.2.5) ; extra == 'all'
Requires-Dist: pytest-cov (>=3.0.0) ; extra == 'all'
Requires-Dist: pytest-xdist (>=2.5.0) ; extra == 'all'
Requires-Dist: pytest-timeout (>=1.4.2) ; extra == 'all'
Requires-Dist: numpy (<1.23,>=1.14.5) ; extra == 'all'
Requires-Dist: pandas (>=1.0) ; extra == 'all'
Requires-Dist: polars ; extra == 'all'
Provides-Extra: dev
Requires-Dist: flake8 (>=3.9.1) ; extra == 'dev'
Requires-Dist: black ; extra == 'dev'
Requires-Dist: pre-commit (>=2.12.1) ; extra == 'dev'
Provides-Extra: test
Requires-Dist: tox ; extra == 'test'
Requires-Dist: flake8 (>=3.9.1) ; extra == 'test'
Requires-Dist: pytest (==6.2.5) ; extra == 'test'
Requires-Dist: pytest-cov (>=3.0.0) ; extra == 'test'
Requires-Dist: pytest-xdist (>=2.5.0) ; extra == 'test'
Requires-Dist: pytest-timeout (>=1.4.2) ; extra == 'test'
Requires-Dist: numpy (<1.23,>=1.14.5) ; extra == 'test'
Requires-Dist: pandas (>=1.0) ; extra == 'test'
Requires-Dist: polars ; extra == 'test'
